glove80/__init__.py
glove80/__main__.py
glove80/base.py
glove80/metadata.py
glove80/py.typed
glove80/cli/__init__.py
glove80/families/__init__.py
glove80/families/shared_finger_specs.py
glove80/families/default/__init__.py
glove80/families/default/layer_data.py
glove80/families/default/layouts.py
glove80/families/default/metadata.json
glove80/families/default/specs.py
glove80/families/glorious_engrammer/__init__.py
glove80/families/glorious_engrammer/custom_behaviors.txt
glove80/families/glorious_engrammer/custom_devicetree.dtsi
glove80/families/glorious_engrammer/layouts.py
glove80/families/glorious_engrammer/metadata.json
glove80/families/glorious_engrammer/specs.py
glove80/families/glorious_engrammer/layers/__init__.py
glove80/families/glorious_engrammer/layers/alpha_layers.py
glove80/families/glorious_engrammer/layers/finger_layers.py
glove80/families/glorious_engrammer/layers/mouse_layers.py
glove80/families/glorious_engrammer/layers/registry.py
glove80/families/glorious_engrammer/layers/utility_layers.py
glove80/families/quantum_touch/__init__.py
glove80/families/quantum_touch/layouts.py
glove80/families/quantum_touch/metadata.json
glove80/families/quantum_touch/layers/__init__.py
glove80/families/quantum_touch/layers/base_layer.py
glove80/families/quantum_touch/layers/finger_layers.py
glove80/families/quantum_touch/layers/hrm.py
glove80/families/quantum_touch/layers/lower_layer.py
glove80/families/quantum_touch/layers/magic_layer.py
glove80/families/quantum_touch/layers/mouse_layers.py
glove80/families/quantum_touch/layers/original_layer.py
glove80/families/quantum_touch/layers/registry.py
glove80/families/quantum_touch/specs/__init__.py
glove80/families/quantum_touch/specs/combos.py
glove80/families/quantum_touch/specs/common.py
glove80/families/quantum_touch/specs/finger_data.py
glove80/families/quantum_touch/specs/hold_taps.py
glove80/families/quantum_touch/specs/input_listeners.py
glove80/families/quantum_touch/specs/macros.py
glove80-2.0.0.dist-info/METADATA
glove80-2.0.0.dist-info/WHEEL
glove80-2.0.0.dist-info/entry_points.txt
glove80-2.0.0.dist-info/RECORD
