Metadata-Version: 2.4
Name: glove80
Version: 2.0.0
Summary: Deterministic Glove80 layout toolkit
Author-email: Bas Nijholt <bas@nijho.lt>
Requires-Python: >=3.10
Requires-Dist: pydantic>=2.12.4
Requires-Dist: rich>=14.2.0
Requires-Dist: typer>=0.12.5
